__init__.py
typedef/block.py
typedef/interactive.py
typedef/rss.py
web/server.py
interactivenlp-0.0.1.dist-info/LICENSE
interactivenlp-0.0.1.dist-info/METADATA
interactivenlp-0.0.1.dist-info/WHEEL
interactivenlp-0.0.1.dist-info/top_level.txt
interactivenlp-0.0.1.dist-info/RECORD
